spatialsorter/__init__.py
spatialsorter/settings.py
spatialsorter/spatialsorter.py
spatialsorter-0.5.0.dist-info/METADATA
spatialsorter-0.5.0.dist-info/WHEEL
spatialsorter-0.5.0.dist-info/RECORD
