Metadata-Version: 2.1
Name: spatialsorter
Version: 0.5.0
Summary: Package for spatially sorting 3d positions
License: MIT
Author: Gereon Tombrink
Author-email: tombrink@igg.uni-bonn.de
Requires-Python: >=3.8.2,<3.12
Classifier: License :: OSI Approved :: MIT License
Classifier: Programming Language :: Python :: 3
Classifier: Programming Language :: Python :: 3.9
Classifier: Programming Language :: Python :: 3.10
Classifier: Programming Language :: Python :: 3.11
Requires-Dist: matplotlib (>=3.7.3)
Requires-Dist: networkx (>=3.1)
Requires-Dist: numpy (>=1.24.4)
Requires-Dist: scipy (>=1.10.1)
Requires-Dist: trajectopy-approx (>=0.5.0,<0.6.0)
Requires-Dist: yaml-dataclass (>=0.1.2,<0.2.0)
